readabledelta.py
readabledelta-0.0.2.dist-info/DESCRIPTION.rst
readabledelta-0.0.2.dist-info/LICENSE.txt
readabledelta-0.0.2.dist-info/METADATA
readabledelta-0.0.2.dist-info/RECORD
readabledelta-0.0.2.dist-info/WHEEL
readabledelta-0.0.2.dist-info/metadata.json
readabledelta-0.0.2.dist-info/top_level.txt
