Metadata-Version: 2.0
Name: readabledelta
Version: 0.0.2
Summary: Human readable modification of timedelta
Home-page: https://github.com/wimglenn/readabledelta
Author: Wim Glenn
Author-email: hey@wimglenn.com
License: UNKNOWN
Platform: UNKNOWN
